getranet_automl/exceptions/__init__.py
getranet_automl/exceptions/exceptions.py
getranet_automl/speech/__init__.py
getranet_automl/speech/transcribe.py
getranet_automl/storage/__init__.py
getranet_automl/storage/storage.py
getranet_automl/translate/__init__.py
getranet_automl/translate/translate.py
getranet_automl-0.1.3.dist-info/LICENSE
getranet_automl-0.1.3.dist-info/WHEEL
getranet_automl-0.1.3.dist-info/METADATA
getranet_automl-0.1.3.dist-info/RECORD
