Metadata-Version: 2.1
Name: getranet-automl
Version: 0.1.3
Summary: Wrapper for important language-centric Google APIs
License: MIT
Author: GeTraNet
Author-email: dev@getranet.de
Requires-Python: >=3.8,<4.0
Classifier: License :: OSI Approved :: MIT License
Classifier: Programming Language :: Python :: 3
Classifier: Programming Language :: Python :: 3.10
Classifier: Programming Language :: Python :: 3.8
Classifier: Programming Language :: Python :: 3.9
Requires-Dist: google-cloud-speech (>=2.9.3,<3.0.0)
Requires-Dist: google-cloud-storage (>=1.42.3,<2.0.0)
Requires-Dist: google-cloud-translate (>=3.4.1,<4.0.0)
Requires-Dist: pydub (>=0.25.1,<0.26.0)
Requires-Dist: python-docx (>=0.8.11,<0.9.0)
Requires-Dist: srt (>=3.5.0,<4.0.0)
Requires-Dist: starlette (>=0.16.0,<0.17.0)
